{
  "countrySlug": "lithuania-lt",
  "politicians": [
    {
      "office": "Head of State",
      "profile": {
        "id": "gitanas-nauseda-head-of-state-lt",
        "slug": "gitanas-nauseda-head-of-state-lt",
        "name": "Gitanas Nausėda",
        "countrySlug": "lithuania-lt",
        "countryName": "Lithuania",
        "office": "Head of State",
        "searchTerms": [
          "gitanas nausėda",
          "head of state",
          "lithuania",
          "lt"
        ],
        "dataSources": [
          {
            "name": "Wikidata",
            "url": "https://www.wikidata.org"
          }
        ],
        "lastUpdated": "2026-05-19T13:30:03.505Z"
      }
    },
    {
      "office": "Minister of Finance",
      "profile": {
        "id": "rimantas-sadzius-minister-of-finance-lt",
        "slug": "rimantas-sadzius-minister-of-finance-lt",
        "name": "Rimantas Šadžius",
        "countrySlug": "lithuania-lt",
        "countryName": "Lithuania",
        "office": "Minister of Finance",
        "searchTerms": [
          "rimantas šadžius",
          "minister of finance",
          "lithuania",
          "lt"
        ],
        "dataSources": [
          {
            "name": "Curated static data",
            "url": "https://en.wikipedia.org"
          }
        ],
        "lastUpdated": "2026-05-19T13:35:21.907Z"
      }
    },
    {
      "office": "Prime Minister",
      "profile": {
        "id": "gintautas-paluckas-prime-minister-lt",
        "slug": "gintautas-paluckas-prime-minister-lt",
        "name": "Gintautas Paluckas",
        "countrySlug": "lithuania-lt",
        "countryName": "Lithuania",
        "office": "Prime Minister",
        "searchTerms": [
          "gintautas paluckas",
          "prime minister",
          "lithuania",
          "lt"
        ],
        "dataSources": [
          {
            "name": "Curated static data",
            "url": "https://en.wikipedia.org"
          }
        ],
        "lastUpdated": "2026-05-19T13:37:01.182Z"
      }
    }
  ]
}
