{
  "countrySlug": "sri-lanka-lk",
  "politicians": [
    {
      "office": "Prime Minister",
      "profile": {
        "id": "harini-amarasuriya-prime-minister-lk",
        "slug": "harini-amarasuriya-prime-minister-lk",
        "name": "Harini Amarasuriya",
        "countrySlug": "sri-lanka-lk",
        "countryName": "Sri Lanka",
        "office": "Prime Minister",
        "searchTerms": [
          "harini amarasuriya",
          "prime minister",
          "sri lanka",
          "lk"
        ],
        "dataSources": [
          {
            "name": "Wikidata",
            "url": "https://www.wikidata.org"
          }
        ],
        "lastUpdated": "2026-05-19T13:30:03.666Z"
      }
    },
    {
      "office": "President",
      "profile": {
        "id": "anura-kumara-dissanayake-president-lk",
        "slug": "anura-kumara-dissanayake-president-lk",
        "name": "Anura Kumara Dissanayake",
        "countrySlug": "sri-lanka-lk",
        "countryName": "Sri Lanka",
        "office": "President",
        "searchTerms": [
          "anura kumara dissanayake",
          "president",
          "sri lanka",
          "lk"
        ],
        "dataSources": [
          {
            "name": "Curated static data",
            "url": "https://en.wikipedia.org"
          }
        ],
        "lastUpdated": "2026-05-19T13:35:22.015Z"
      }
    }
  ]
}
