{
  "profile": {
    "id": "dahll",
    "slug": "christian-dahll",
    "name": "Christian Dahll",
    "bio": "COO since January 2022. Joined 2020 Bulkers in January 2020 as Head of Commercial Operations. Former Höegh Autoliners.",
    "currentTitle": "Chief Operating Officer",
    "currentCompanySlug": "2020-bulkers",
    "currentCompanyName": "2020 Bulkers Ltd",
    "affiliations": [
      {
        "companySlug": "2020-bulkers",
        "companyName": "2020 Bulkers Ltd",
        "title": "Chief Operating Officer"
      }
    ],
    "dataSources": [],
    "lastUpdated": "2026-05-18T15:26:36.045Z"
  }
}